paynow/__init__.py
paynow/__main__.py
paynow/model.py
paynow-1.0.7.dist-info/LICENSE.txt
paynow-1.0.7.dist-info/METADATA
paynow-1.0.7.dist-info/WHEEL
paynow-1.0.7.dist-info/top_level.txt
paynow-1.0.7.dist-info/RECORD
