Metadata-Version: 2.1
Name: paynow
Version: 1.0.7
Summary: Paynow Python SDK
Home-page: https://gitlab.com/paynow-developer-hub/Paynow-Python-SDK
Author: WebDev Projects
Author-email: pkg-dev@webdevworld.com
Project-URL: Bug Reports, https://gitlab.com/paynow-developer-hub/Paynow-Python-SDK/issues
Project-URL: Source, https://gitlab.com/paynow-developer-hub/Paynow-Python-SDK
Keywords: paynow-api paynow-zimbabwe paynow-zimbabwe-api paynow-zimbabwe-sdk
Classifier: Development Status :: 5 - Production/Stable
Classifier: Intended Audience :: Developers
Classifier: License :: OSI Approved :: MIT License
Classifier: Topic :: Software Development :: Libraries :: Python Modules
Classifier: Programming Language :: Python :: 2
Classifier: Programming Language :: Python :: 2.7
Classifier: Programming Language :: Python :: 3
Classifier: Programming Language :: Python :: 3.4
Classifier: Programming Language :: Python :: 3.5
Classifier: Programming Language :: Python :: 3.6
License-File: LICENSE.txt
Requires-Dist: requests
Requires-Dist: six
